zen/__init__.py
zen/demo_animations.py
zen/cli/__init__.py
zen/cli/main.py
zen/core/__init__.py
zen/core/animation_config.py
zen/core/exceptions.py
zen/core/installer.py
zen/core/logger.py
zen/schemas/__init__.py
zen/schemas/component.py
zen/schemas/registry.py
zenive-1.1.1.dist-info/licenses/LICENSE
zenive-1.1.1.dist-info/METADATA
zenive-1.1.1.dist-info/WHEEL
zenive-1.1.1.dist-info/entry_points.txt
zenive-1.1.1.dist-info/top_level.txt
zenive-1.1.1.dist-info/RECORD
