Metadata-Version: 2.4
Name: zenive
Version: 1.1.1
Summary: A component registry for discovering, installing, and managing reusable code components
Home-page: https://github.com/TheRaj71/Zenive
Author: TheRaj71
Author-email: TheRaj71 <theraj714@zohomail.in>
License: MIT License
Project-URL: Homepage, https://github.com/TheRaj71/Zenive
Project-URL: Bug Tracker, https://github.com/TheRaj71/Zenive/issues
Project-URL: Source Code, https://github.com/TheRaj71/Zenive
Project-URL: Documentation, https://github.com/TheRaj71/Zenive#readme
Keywords: components,registry,shadcn,python,cli,zen
Classifier: Development Status :: 5 - Production/Stable
Classifier: Intended Audience :: Developers
Classifier: License :: OSI Approved :: MIT License
Classifier: Operating System :: OS Independent
Classifier: Programming Language :: Python :: 3
Classifier: Programming Language :: Python :: 3.8
Classifier: Programming Language :: Python :: 3.9
Classifier: Programming Language :: Python :: 3.10
Classifier: Programming Language :: Python :: 3.11
Classifier: Programming Language :: Python :: 3.12
Classifier: Topic :: Software Development :: Libraries :: Python Modules
Classifier: Topic :: Software Development :: Code Generators
Classifier: Topic :: System :: Software Distribution
Requires-Python: >=3.8
License-File: LICENSE
Requires-Dist: click>=8.0.0
Requires-Dist: requests>=2.25.0
Requires-Dist: pydantic>=2.0.0
Requires-Dist: PyYAML>=6.0.0
Requires-Dist: rich>=13.0.0
Requires-Dist: packaging>=21.0.0
Dynamic: author
Dynamic: home-page
Dynamic: license-file
Dynamic: requires-python
